paroxython/__init__.py
paroxython/assess_costs.py
paroxython/cli.py
paroxython/cli_collect.py
paroxython/cli_recommend.py
paroxython/cli_tag.py
paroxython/compare_spans.py
paroxython/derived_labels_db.py
paroxython/filter_programs.py
paroxython/flatten_ast.py
paroxython/goodies.py
paroxython/label_programs.py
paroxython/list_programs.py
paroxython/make_db.py
paroxython/map_taxonomy.py
paroxython/normalize_predicate.py
paroxython/parse_program.py
paroxython/preprocess_source.py
paroxython/recommend_programs.py
paroxython/resources/spec.md
paroxython/resources/taxonomy.tsv
paroxython/user_types.py
paroxython-0.7.2.dist-info/LICENSE
paroxython-0.7.2.dist-info/WHEEL
paroxython-0.7.2.dist-info/entry_points.txt
paroxython-0.7.2.dist-info/METADATA
paroxython-0.7.2.dist-info/RECORD
