Metadata-Version: 2.1
Name: paroxython
Version: 0.7.2
Summary: Search Python code for algorithmic features
Home-page: https://github.com/laowantong/paroxython/
License: MIT
Keywords: education,static-analysis,algorithmic,metaprogramming,python,taxonomic-classification,knowledge-management
Author: Aristide Grange
Requires-Python: >=3.8,<4.0
Classifier: Development Status :: 5 - Production/Stable
Classifier: Environment :: Console
Classifier: Framework :: IPython
Classifier: Intended Audience :: Education
Classifier: License :: OSI Approved :: MIT License
Classifier: Natural Language :: English
Classifier: Operating System :: OS Independent
Classifier: Programming Language :: Python :: 3
Classifier: Programming Language :: Python :: 3.8
Classifier: Programming Language :: Python :: 3.9
Classifier: Programming Language :: Python :: 3.10
Classifier: Programming Language :: Python :: 3.11
Classifier: Programming Language :: Python :: 3.8
Classifier: Programming Language :: Python :: 3.9
Classifier: Programming Language :: SQL
Classifier: Topic :: Database
Classifier: Topic :: Education
Classifier: Typing :: Typed
Requires-Dist: docopt (>=0.6.2,<0.7.0)
Requires-Dist: regex (>=2022.8.17,<2023.0.0)
Requires-Dist: typing-extensions (>=4.3.0,<5.0.0)
Project-URL: Repository, https://github.com/laowantong/paroxython/
Project-URL: issues, https://github.com/laowantong/paroxython/issues
